<?xml version="1.0" encoding="UTF-8"?>
<item><pubDate>Thu, 13 Sep 2012 22:14:56 +0700</pubDate><title>Android bricks</title><url>partner5</url><meta>9buttons, 9 buttons, разработка мобильных приложений, Android, Windows Mobile, iOS, Bada, Android bricks</meta><metad>9 buttons - наши партнёры: Android bricks</metad><menu>sidebar</menu><menuStatus/><template>post.php</template><parent>partners</parent><content>&amp;lt;h5&amp;gt;
	&amp;lt;noindex&amp;gt;&amp;lt;a href=&amp;quot;http://apkdev.tumblr.com/&amp;quot; target=&amp;quot;_blank&amp;quot;&amp;gt;&amp;lt;img alt=&amp;quot;http://apkdev.tumblr.com/&amp;quot; class=&amp;quot;border-shadowed post-image&amp;quot; src=&amp;quot;http://9buttons.kz/data/uploads/partners/4androids.png&amp;quot; title=&amp;quot;Нетривиальные вопросы разработки&amp;quot; /&amp;gt;&amp;lt;br /&amp;gt;
	&amp;lt;br /&amp;gt;
	Android bricks&amp;lt;/a&amp;gt;&amp;lt;/noindex&amp;gt;&amp;lt;/h5&amp;gt;
&amp;lt;p&amp;gt;
	А вот это наш маленький секрет. Эх, да! Да, да, да! Мы тоже не можем знать всего. А когда возникают вопросы, читаем этот блог. Он нас уже не раз спасал :) Разработчикам советуем.&amp;lt;/p&amp;gt;
</content><private/><menuOrder><![CDATA[2]]></menuOrder></item>
